<?xml version="1.0" encoding="utf-8"?><asx:abap xmlns:asx="http://www.sap.com/abapxml">
<asx:values>
<TADIR>
<TADIR>
<PGMID>R3TR</PGMID>
<OBJECT>PROG</OBJECT>
<OBJ_NAME>ZSTOCK_TAX_ANALYSIS</OBJ_NAME>
<KORRNUM></KORRNUM>
<SRCSYSTEM>A4H</SRCSYSTEM>
<AUTHOR>DEVELOPER</AUTHOR>
<SRCDEP></SRCDEP>
<DEVCLASS>ZSTOCKS</DEVCLASS>
<GENFLAG></GENFLAG>
<EDTFLAG></EDTFLAG>
<CPROJECT> S</CPROJECT>
<MASTERLANG>E</MASTERLANG>
<VERSID></VERSID>
<PAKNOCHECK></PAKNOCHECK>
<OBJSTABLTY></OBJSTABLTY>
<COMPONENT></COMPONENT>
<CRELEASE></CRELEASE>
<DELFLAG></DELFLAG>
<TRANSLTTXT></TRANSLTTXT>
<CREATED_ON>2021-09-11</CREATED_ON>
<CHECK_DATE>2021-09-11</CHECK_DATE>
<CHECK_CFG></CHECK_CFG>
</TADIR>
</TADIR>
<TRDIR>
<TRDIR>
<NAME>ZSTOCK_TAX_ANALYSIS</NAME>
<SQLX></SQLX>
<EDTX></EDTX>
<VARCL>X</VARCL>
<DBAPL></DBAPL>
<DBNA></DBNA>
<CLAS></CLAS>
<TYPE></TYPE>
<OCCURS></OCCURS>
<SUBC>1</SUBC>
<APPL></APPL>
<SECU></SECU>
<CNAM>DEVELOPER</CNAM>
<CDAT>2021-09-11</CDAT>
<UNAM>DEVELOPER</UNAM>
<UDAT>2021-09-13</UDAT>
<VERN>000030</VERN>
<LEVL></LEVL>
<RSTAT>K</RSTAT>
<RMAND>001</RMAND>
<RLOAD>E</RLOAD>
<FIXPT>X</FIXPT>
<SSET></SSET>
<SDATE>2021-09-13</SDATE>
<STIME>221152</STIME>
<IDATE>2021-09-13</IDATE>
<ITIME>211740</ITIME>
<LDBNAME></LDBNAME>
<UCCHECK>X</UCCHECK>
</TRDIR>
</TRDIR>
<TRDIRT>
<TRDIRT>
<NAME>ZSTOCK_TAX_ANALYSIS</NAME>
<SPRSL>E</SPRSL>
<TEXT>Stock Tax Analysis</TEXT>
</TRDIRT>
</TRDIRT>
</asx:values>
</asx:abap>